{
    "LatticeSize" : {
        "x" : 28,
        "y" : 28,
        "z" : 28,
        "t" : 56
    },
    "SubLatticeSize" : {
        "x" : 7,
        "y" : 7,
        "z" : 7,
        "t" : 7
    },
    "App" : {
        "type"   : "PGFG",
        "params" : {
            "startType"  : "Cold",
            "MCSteps"    : 300000,
            "NConf"      : 500,
            "SU3eps"     : 0.25,
            "thermSteps" : 10000
        }
    },
    "Action" : {
        "type"   : "puregauge",
        "params" : {
            "beta" : 6.1
        }
    },
    "Observables" : [
        "superobs"
    ],
    "OutputDir" : "/mnt/ls15/scratch/users/pederiva/masterData/28_b6.10_512" 
}
